diveharder/__init__.py
diveharder/api/base.py
diveharder/api/campaings.py
diveharder/api/dispatches.py
diveharder/api/exceptions.py
diveharder/api/planets.py
diveharder/api/stats.py
diveharder/api/status.py
diveharder/api/updates.py
diveharder/api/war_info.py
diveharder/api_client.py
diveharder/cli.py
diveharder/constants.py
diveharder/enums.py
diveharder/objects.py
diveharder/utils.py
diveharder-0.1.2.dist-info/entry_points.txt
diveharder-0.1.2.dist-info/LICENSE
diveharder-0.1.2.dist-info/METADATA
diveharder-0.1.2.dist-info/WHEEL
diveharder-0.1.2.dist-info/RECORD
