Metadata-Version: 2.1
Name: diveharder
Version: 0.1.2
Summary: A Helldivers 2 API wrapper using the Diveharder API
Home-page: https://github.com/ajxd2/diveharder-wrapper
License: MIT
Keywords: helldivers 2,api,wrapper,diveharder,community
Author: AJXD2
Author-email: anthonyjohnkovach@gmail.com
Requires-Python: >=3.11,<4.0
Classifier: Intended Audience :: Developers
Classifier: License :: OSI Approved :: MIT License
Classifier: Operating System :: OS Independent
Classifier: Programming Language :: Python :: 3
Classifier: Programming Language :: Python :: 3.11
Classifier: Topic :: Games/Entertainment
Classifier: Topic :: System :: Networking
Classifier: Typing :: Typed
Requires-Dist: fire (>=0.6.0,<0.7.0)
Requires-Dist: requests (>=2.32.3,<3.0.0)
Requires-Dist: rich (>=13.7.1,<14.0.0)
